Alaea/Blogging.py
Alaea/S_DateTime.py
Alaea/__init__.py
Alaea/commonCode.py
Alaea/cprintfs.py
Alaea/processBar.py
Alaea/read_conf.py
Alaea/server_info.py
Alaea/Pyshell/RS_File.py
Alaea/Pyshell/__init__.py
Alaea/SameAsMATLAB/CoorTrans.py
Alaea/SameAsMATLAB/__init__.py
Alaea/SameAsMATLAB/calculatefuns.py
Alaea/Standard/__init__.py
Alaea/Standard/xr_attrs.py
Alaea/Standard/xr_ice.py
Alaea/Standard/xr_wave.py
Alaea/exutils/__init__.py
Alaea/exutils/Interp/Interp_g2s.py
Alaea/exutils/Interp/Interp_s2g.py
Alaea/exutils/Interp/__init__.py
Alaea/pFVCOM/__init__.py
Alaea/pFVCOM/fvcom_class.py
Alaea/pFVCOM/fvcom_image.py
Alaea/pFVCOM/fvcom_load.py
Alaea/pFVCOM/fvcom_tools.py
Alaea/pFVCOM/writeFile.py
Alaea/tools/P_params.py
Alaea/tools/Read.py
Alaea/tools/__init__.py
Alaea/tools/download_check.py
Alaea/tools/geo_distance.py
Alaea/tools/kml2shp.py
Alaea/warningTools/__init__.py
alaea-2.3.3.dist-info/METADATA
alaea-2.3.3.dist-info/WHEEL
alaea-2.3.3.dist-info/top_level.txt
alaea-2.3.3.dist-info/RECORD
